bqflow/__init__.py
bqflow/_helper.py
bqflow/client.py
bqflow/fields.py
bqflow/load.py
bqflow/main.py
bqflow/parameter.py
bqflow/procon.py
bqflow/report.py
bqflow/task.py
bqflow/tracer.py
bq_flow-0.1.1.dist-info/entry_points.txt
bq_flow-0.1.1.dist-info/WHEEL
bq_flow-0.1.1.dist-info/METADATA
bq_flow-0.1.1.dist-info/RECORD
